MANIFEST.in
Makefile
atom.py
colorexcept.py
conf.py
f_core.py
f_core.rst
f_dielectric.py
f_extract.py
f_extract.rst
f_tests.py
f_tests.rst
f_timeseries.py
f_timeseries.rst
f_viscosity.py
index.rst
moremath.py
output_tracker.py
setup.py
finley.egg-info/PKG-INFO
finley.egg-info/SOURCES.txt
finley.egg-info/dependency_links.txt
finley.egg-info/requires.txt
finley.egg-info/top_level.txt