Metadata-Version: 1.1
Name: finley
Version: 0.1-r2696
Summary: Command line analyzer for large molecular dynamics trajectories with DCD support.
Home-page: http://guido.vonrudorff.de/finley/
Author: Guido Falk von Rudorff
Author-email: guido@vonrudorff.de
License: GPL 2
Keywords: DCD,PDB,PSF
Platform: UNKNOWN
Classifier: Development Status :: 4 - Beta
Requires: MDAnalysis
